example_module/__init__.py
example_module/__main__.py
example_module/add_two_numbers.py
example_module/analyze_file_pipeline.py
module_for_cli_test/__init__.py
module_for_cli_test/__main__.py
module_for_cli_test/add_two_numbers.py
module_for_cli_test/analyze_file_pipeline.py
simppl/__init__.py
simppl/cli.py
simppl/simple_pipeline.py
tests/__init__.py
tests/test_cli_auto_discovery_mode.py
tests/test_cli_explicit_mode.py
tests/test_simple_pipeline.py
simppl-1.0.7.dist-info/LICENSE
simppl-1.0.7.dist-info/METADATA
simppl-1.0.7.dist-info/WHEEL
simppl-1.0.7.dist-info/top_level.txt
simppl-1.0.7.dist-info/RECORD
