Metadata-Version: 2.1
Name: simppl
Version: 1.0.7
Summary: simple commands execution pipeline, coupled with unified command-line-interface entry-point
Home-page: https://github.com/nrgene/simppl
Author: NRGene
Author-email: open-source@nrgene.com
Classifier: Programming Language :: Python :: 3
Classifier: License :: OSI Approved :: MIT License
Classifier: Operating System :: OS Independent
Requires-Python: >3.6
License-File: LICENSE
Requires-Dist: colorama
Requires-Dist: pytest
